[
  {
    "id": "chunk_0",
    "chunk_index": 0,
    "source": "https://suckhoedoisong.vn/hoi-dap-tre-cham-noi-lieu-co-mac-tu-ky-169230404102526476.htm",
    "source_type": "docs",
    "url": "https://suckhoedoisong.vn/hoi-dap-tre-cham-noi-lieu-co-mac-tu-ky-169230404102526476.htm",
    "data_type": "web",
    "created_at": "2026-05-02T17:19:32.694461+00:00",
    "text": "[Hỏi đáp] Trẻ chậm nói liệu có mắc tự kỷ?\n \n \n \n \n \n \n \n \nHà Nội\n \n \n \n \n \n \n \n \n \n Thông tin tài khoản \n Danh sách bài đã lưu \n Danh sách bài đã xem \n Hoạt động bình luận \nĐăng xuất\n \n \n \n \n \n \n \n \n Y tế \n Thời sự \n Tra cứu bệnh \n Sức khỏe TV \n Y học 360 \n Dược \n Y học cổ truyền \n Giới tính \n Dinh dưỡng \n Khỏe - Đẹp \n Phòng mạch online \n Thị trường \n \n \n \n \n \n \n \nThời sự\n Xã hội \n \n Pháp luật \n \n Quốc tế \nY tế \n Tin nóng y tế \n \n Thành tựu y khoa \n \n Blog thầy thuốc \n \n Sự hi sinh thầm lặng"
  },
  {
    "id": "chunk_1",
    "chunk_index": 1,
    "source": "https://suckhoedoisong.vn/hoi-dap-tre-cham-noi-lieu-co-mac-tu-ky-169230404102526476.htm",
    "source_type": "docs",
    "url": "https://suckhoedoisong.vn/hoi-dap-tre-cham-noi-lieu-co-mac-tu-ky-169230404102526476.htm",
    "data_type": "web",
    "created_at": "2026-05-02T17:19:32.694461+00:00",
    "text": "Quốc tế \nY tế \n Tin nóng y tế \n \n Thành tựu y khoa \n \n Blog thầy thuốc \n \n Sự hi sinh thầm lặng \n \n Camera bệnh viện \nTra cứu bệnh\nSức khỏe TV\n Tọa đàm \n \n Giao lưu \n \n Livestream \nDược\n An toàn dùng thuốc \n \n Thông tin dược học \n \n Thuốc mới \n \n Vaccine \nY học cổ truyền\n Thầy giỏi – thuốc hay \n \n Bệnh viện - phòng khám \n \n Cây thuốc quanh ta \n \n Chữa bệnh không dùng thuốc \nMultimedia\n Emagazine \n \n Video \n \n Infographic \nY học 360\n Bệnh người cao tuổi \n \n Bệnh thường gặp \n \n Bệnh phụ nữ"
  },
  {
    "id": "chunk_2",
    "chunk_index": 2,
    "source": "https://suckhoedoisong.vn/hoi-dap-tre-cham-noi-lieu-co-mac-tu-ky-169230404102526476.htm",
    "source_type": "docs",
    "url": "https://suckhoedoisong.vn/hoi-dap-tre-cham-noi-lieu-co-mac-tu-ky-169230404102526476.htm",
    "data_type": "web",
    "created_at": "2026-05-02T17:19:32.694461+00:00",
    "text": "Video \n \n Infographic \nY học 360\n Bệnh người cao tuổi \n \n Bệnh thường gặp \n \n Bệnh phụ nữ \n \n Bệnh nam giới \n \n Bệnh trẻ em \n \n Sức khỏe tâm hồn \n \n Ung thư \nKhỏe - Đẹp\n Mỹ phẩm \n \n Thẩm mỹ \n \n Bài tập khỏe đẹp \nDinh dưỡng\n Dinh dưỡng mẹ và bé \n \n Dinh dưỡng người cao tuổi \n \n Chế độ ăn người bệnh \n \n Cảnh giác thực phẩm \n \n Thực phẩm chức năng \nGiới tính\n Hỏi đáp phòng the \n \n Sức khỏe sinh sản \n \n Bệnh lây truyền \nPhòng mạch online\nThị trường\n Nhãn hàng sai phạm \n \n Doanh nghiệp"
  },
  {
    "id": "chunk_3",
    "chunk_index": 3,
    "source": "https://suckhoedoisong.vn/hoi-dap-tre-cham-noi-lieu-co-mac-tu-ky-169230404102526476.htm",
    "source_type": "docs",
    "url": "https://suckhoedoisong.vn/hoi-dap-tre-cham-noi-lieu-co-mac-tu-ky-169230404102526476.htm",
    "data_type": "web",
    "created_at": "2026-05-02T17:19:32.694461+00:00",
    "text": "Bệnh lây truyền \nPhòng mạch online\nThị trường\n Nhãn hàng sai phạm \n \n Doanh nghiệp \nNhịp cầu Nhân ái\nVăn hóa – Giải trí\nChuyên trang gia đình\nĐời sống\n \n \n Y học 360 \n \n \n \nBệnh người cao tuổi\n \nBệnh thường gặp\n \nBệnh phụ nữ\n \nBệnh nam giới\n \nBệnh trẻ em\n \nSức khỏe tâm hồn\n \nUng thư\n \n \n \n \n \n \n \n \n \n \n \n \n \n \n[Hỏi đáp] Trẻ chậm nói liệu có mắc tự kỷ?\n18-04-2023 10:00 | \n \nY học 360"
  },
  {
    "id": "chunk_4",
    "chunk_index": 4,
    "source": "https://suckhoedoisong.vn/hoi-dap-tre-cham-noi-lieu-co-mac-tu-ky-169230404102526476.htm",
    "source_type": "docs",
    "url": "https://suckhoedoisong.vn/hoi-dap-tre-cham-noi-lieu-co-mac-tu-ky-169230404102526476.htm",
    "data_type": "web",
    "created_at": "2026-05-02T17:19:32.694461+00:00",
    "text": "[Hỏi đáp] Trẻ chậm nói liệu có mắc tự kỷ?\n18-04-2023 10:00 | \n \nY học 360\n \n \nHiện nay, số lượng trẻ chậm nói, nói ngọng, giao tiếp kém đang ngày càng gia tăng. Điều đáng lo ngại hơn khi phần lớn số trẻ chậm nói khi thăm khám đều được chẩn đoán mắc tự kỷ ? Mời quý độc giả tìm hiểu ngay nguyên do trong bài viết dưới đây.\nTrẻ chậm nói có nguy cơ cao mắc tự kỷ đang là nỗi lo lắng của nhiều gia đình\nTại sao trẻ chậm nói dễ mắc tự kỷ?"
  },
  {
    "id": "chunk_5",
    "chunk_index": 5,
    "source": "https://suckhoedoisong.vn/hoi-dap-tre-cham-noi-lieu-co-mac-tu-ky-169230404102526476.htm",
    "source_type": "docs",
    "url": "https://suckhoedoisong.vn/hoi-dap-tre-cham-noi-lieu-co-mac-tu-ky-169230404102526476.htm",
    "data_type": "web",
    "created_at": "2026-05-02T17:19:32.694461+00:00",
    "text": "Tại sao trẻ chậm nói dễ mắc tự kỷ? \nNhiều nghiên cứu chỉ ra rằng, trẻ chậm nói có nguy cơ cao hơn mắc chứng tự kỷ (ASD) hoặc rối loạn phổ tự kỷ (ASD) so với trẻ phát triển ngôn ngữ bình thường. Một số lý do cho điều này có thể bao gồm:\n   - Trẻ thiếu kết nối xã hội:\n Trẻ chậm nói, trẻ khó bật âm thường thiếu các kết nối xã hội khiến khả năng giao tiếp hạn chế. Tình trạng này kéo dài dẫn đến nguy cơ cao mắc tự kỷ ở trẻ.\n   - Trẻ gặp khó khăn trong giao tiếp:"
  },
  {
    "id": "chunk_6",
    "chunk_index": 6,
    "source": "https://suckhoedoisong.vn/hoi-dap-tre-cham-noi-lieu-co-mac-tu-ky-169230404102526476.htm",
    "source_type": "docs",
    "url": "https://suckhoedoisong.vn/hoi-dap-tre-cham-noi-lieu-co-mac-tu-ky-169230404102526476.htm",
    "data_type": "web",
    "created_at": "2026-05-02T17:19:32.694461+00:00",
    "text": "- Trẻ gặp khó khăn trong giao tiếp: \nTrẻ chậm nói thường gặp khó khăn trong việc truyền đạt mong muốn của bản thân với người xung quanh.  Do vốn từ ít, phát âm kém, nói ngọng, nói lắp,... khiến người khác không nghe và hiểu được ý của trẻ điều khiến trẻ cảm thấy bị cô lập.\n   - Thiếu vi chất dinh dưỡng"
  },
  {
    "id": "chunk_7",
    "chunk_index": 7,
    "source": "https://suckhoedoisong.vn/hoi-dap-tre-cham-noi-lieu-co-mac-tu-ky-169230404102526476.htm",
    "source_type": "docs",
    "url": "https://suckhoedoisong.vn/hoi-dap-tre-cham-noi-lieu-co-mac-tu-ky-169230404102526476.htm",
    "data_type": "web",
    "created_at": "2026-05-02T17:19:32.694461+00:00",
    "text": "- Thiếu vi chất dinh dưỡng\n: Thiếu các vi chất thiết yếu cho não bộ khiến các vùng não hoạt động kém. Đặc biệt dễ đứt gãy các liên kết thần kinh dẫn đến vùng ngôn ngữ của trẻ hoạt động 1 cách trì trệ. Lâu dần sẽ khiến trẻ có nguy cơ mắc tự kỷ.\nCác phương pháp giúp trẻ nhanh biết nói đẩy lùi tự kỷ"
  },
  {
    "id": "chunk_8",
    "chunk_index": 8,
    "source": "https://suckhoedoisong.vn/hoi-dap-tre-cham-noi-lieu-co-mac-tu-ky-169230404102526476.htm",
    "source_type": "docs",
    "url": "https://suckhoedoisong.vn/hoi-dap-tre-cham-noi-lieu-co-mac-tu-ky-169230404102526476.htm",
    "data_type": "web",
    "created_at": "2026-05-02T17:19:32.694461+00:00",
    "text": "Các phương pháp giúp trẻ nhanh biết nói đẩy lùi tự kỷ \nTự kỷ là một rối loạn phát triển trên phạm vi rộng và có thể ảnh hưởng đến nhiều khía cạnh của cuộc sống của trẻ. Việc gia đình kết hợp các biện pháp can thiệp kịp thời giúp trẻ nhanh biết nói, sớm bật âm, tăng khả năng giao tiếp nói đẩy lùi tự kỷ là điều vô cùng quan trọng. Các bậc phụ huynh có thể tham khảo một số phương pháp sau:\nDành nhiều thời gian cho trẻ"
  },
  {
    "id": "chunk_9",
    "chunk_index": 9,
    "source": "https://suckhoedoisong.vn/hoi-dap-tre-cham-noi-lieu-co-mac-tu-ky-169230404102526476.htm",
    "source_type": "docs",
    "url": "https://suckhoedoisong.vn/hoi-dap-tre-cham-noi-lieu-co-mac-tu-ky-169230404102526476.htm",
    "data_type": "web",
    "created_at": "2026-05-02T17:19:32.694461+00:00",
    "text": "Dành nhiều thời gian cho trẻ\nTương tác nhiều với trẻ là một trong những cách hiệu quả để giúp trẻ phát triển ngôn ngữ, tăng khả năng giao tiếp. Các bậc phụ huynh nên tạo cơ hội để tương tác với trẻ bằng cách tạo ra các hoạt động như chơi cùng trẻ, nói chuyện với trẻ, đọc sách cho trẻ nghe,... Tương tác nhiều với trẻ sẽ giúp trẻ cảm thấy an toàn và tin tưởng, và khuyến khích trẻ tham gia các hoạt động xã hội.\nCha mẹ thường xuyên giao tiếp, trò chuyện với con giúp con nhanh biết nói"
  },
  {
    "id": "chunk_10",
    "chunk_index": 10,
    "source": "https://suckhoedoisong.vn/hoi-dap-tre-cham-noi-lieu-co-mac-tu-ky-169230404102526476.htm",
    "source_type": "docs",
    "url": "https://suckhoedoisong.vn/hoi-dap-tre-cham-noi-lieu-co-mac-tu-ky-169230404102526476.htm",
    "data_type": "web",
    "created_at": "2026-05-02T17:19:32.694461+00:00",
    "text": "Cha mẹ thường xuyên giao tiếp, trò chuyện với con giúp con nhanh biết nói\nSử dụng ngôn ngữ đơn giản và dễ hiểu\nKhi dạy trẻ tại nhà cha mẹ cần lưu ý phát âm chuẩn, chậm, to, rõ ràng, dễ hiểu tránh nói ngọng hay nhại lại lời trẻ khiến trẻ hiểu lầm là trẻ đang nói đúng. Do đó, từ những giao tiếp hàng ngày giữa các thành viên trong gia đình cũng cần lưu tâm để giúp trẻ nhanh ghi nhớ, gia tăng vốn từ, giúp trẻ dễ dàng hình dung và nhanh biết nói.\nĐọc truyện cùng trẻ"
  },
  {
    "id": "chunk_11",
    "chunk_index": 11,
    "source": "https://suckhoedoisong.vn/hoi-dap-tre-cham-noi-lieu-co-mac-tu-ky-169230404102526476.htm",
    "source_type": "docs",
    "url": "https://suckhoedoisong.vn/hoi-dap-tre-cham-noi-lieu-co-mac-tu-ky-169230404102526476.htm",
    "data_type": "web",
    "created_at": "2026-05-02T17:19:32.694461+00:00",
    "text": "Đọc truyện cùng trẻ\nĐọc truyện cùng trẻ, cùng trẻ hóa thân thành các nhân vật trong câu truyện ngoài việc phát huy trí tưởng tượng tuyệt vời thì đọc truyện còn giúp trẻ phát triển kỹ năng ngôn ngữ. Tuy nhiên, các bậc phụ huynh nên lựa chọn những truyện có nhiều màu sắc, các nhân vật sự kiện sau trong câu chuyện sau khi đọc xong rút ra được nhiều bài học từ những câu chuyện đó.\nChơi trò đóng vai"
  },
  {
    "id": "chunk_12",
    "chunk_index": 12,
    "source": "https://suckhoedoisong.vn/hoi-dap-tre-cham-noi-lieu-co-mac-tu-ky-169230404102526476.htm",
    "source_type": "docs",
    "url": "https://suckhoedoisong.vn/hoi-dap-tre-cham-noi-lieu-co-mac-tu-ky-169230404102526476.htm",
    "data_type": "web",
    "created_at": "2026-05-02T17:19:32.694461+00:00",
    "text": "Chơi trò đóng vai\nCha mẹ ngoài dạy con bằng các phương pháp trên có thể thay đổi bằng trò chơi đóng vai theo các nhân vật như: Bác sĩ, cảnh sát, lính cứu hỏa,... Các hoạt động này như trò chơi xã hội ngoài dạy trẻ phát triển ngôn ngữ đồng thời dạy trẻ phát triển kỹ năng xã hội, kỹ năng tương tác và biết chia sẻ giúp đỡ người xung quanh. \nGiải pháp từ thảo dược giúp trẻ tăng cường vi chất tốt cho não"
  },
  {
    "id": "chunk_13",
    "chunk_index": 13,
    "source": "https://suckhoedoisong.vn/hoi-dap-tre-cham-noi-lieu-co-mac-tu-ky-169230404102526476.htm",
    "source_type": "docs",
    "url": "https://suckhoedoisong.vn/hoi-dap-tre-cham-noi-lieu-co-mac-tu-ky-169230404102526476.htm",
    "data_type": "web",
    "created_at": "2026-05-02T17:19:32.694461+00:00",
    "text": "Giải pháp từ thảo dược giúp trẻ tăng cường vi chất tốt cho não  \nHiện nay, số lượng trẻ chậm nói được chẩn đoán mắc tự kỷ ngày càng cao. Các bậc phụ huynh ngày nay bên cạnh áp dụng các phương pháp dạy trẻ chậm nói tại nhà, nhiều bậc phụ huynh đã bổ sung thêm các sản phẩm hỗ trợ từ thảo dược cho con.\nBổ sung vi chất từ thảo dược giúp hỗ trợ hoạt huyết, tăng cường hoạt chất và năng lượng cho não. Trong đó, cần kể đến:\n   - Đinh lăng (thành phần chính"
  },
  {
    "id": "chunk_14",
    "chunk_index": 14,
    "source": "https://suckhoedoisong.vn/hoi-dap-tre-cham-noi-lieu-co-mac-tu-ky-169230404102526476.htm",
    "source_type": "docs",
    "url": "https://suckhoedoisong.vn/hoi-dap-tre-cham-noi-lieu-co-mac-tu-ky-169230404102526476.htm",
    "data_type": "web",
    "created_at": "2026-05-02T17:19:32.694461+00:00",
    "text": "- Đinh lăng (thành phần chính\n): Hỗ trợ tăng dẫn truyền thần kinh giúp gia tăng các liên kết thần kinh trong não bộ. Đồng thời hỗ trợ điều hòa biên độ sóng não, điều hòa hành vi, cảm xúc của trẻ.\n   - Thăng ma, Ginkgo biloba: \nHỗ trợ\n \ncải thiện tuần hoàn máu não\n,\n cung cấp oxy cho tế bào não, giúp trẻ tăng khả năng tập trung, ghi nhớ, giao tiếp tốt.\n   - Vi chất thiết yếu:"
  },
  {
    "id": "chunk_15",
    "chunk_index": 15,
    "source": "https://suckhoedoisong.vn/hoi-dap-tre-cham-noi-lieu-co-mac-tu-ky-169230404102526476.htm",
    "source_type": "docs",
    "url": "https://suckhoedoisong.vn/hoi-dap-tre-cham-noi-lieu-co-mac-tu-ky-169230404102526476.htm",
    "data_type": "web",
    "created_at": "2026-05-02T17:19:32.694461+00:00",
    "text": "- Vi chất thiết yếu:\n Natri succinate, Taurine, Vitamin B6, Acid folic, Coenzyme Q10 có vai trò tổng hợp các chất dẫn truyền thần kinh và enzyme thiết yếu cho não, điều hòa hoạt động não bộ, gia tăng kết nối thần kinh giúp trẻ nhanh biết nói, phát triển khả năng giao tiếp.\nBổ sung thảo dược và các vi chất thiết yếu cho não bộ hỗ trợ trẻ nhanh biết nói\nThực phẩm bảo vệ sức khỏe Vương Não Khang"
  },
  {
    "id": "chunk_16",
    "chunk_index": 16,
    "source": "https://suckhoedoisong.vn/hoi-dap-tre-cham-noi-lieu-co-mac-tu-ky-169230404102526476.htm",
    "source_type": "docs",
    "url": "https://suckhoedoisong.vn/hoi-dap-tre-cham-noi-lieu-co-mac-tu-ky-169230404102526476.htm",
    "data_type": "web",
    "created_at": "2026-05-02T17:19:32.694461+00:00",
    "text": "Thực phẩm bảo vệ sức khỏe Vương Não Khang\n có sự kết hợp giữa Đinh lăng, Thăng ma, Ginkgo biloba và Taurine, Natri succinate, Acid folic, Coenzym Q10... Sản phẩm có công dụng hỗ trợ hoạt huyết, tăng cường vi chất và năng lượng cho não bộ, hỗ trợ cải thiện giấc ngủ…\nĐể biết thêm thông tin chi tiết về sản phẩm Vương Não Khang cũng như các giải pháp giúp trẻ nhanh biết nói, giao tiếp tốt, cha mẹ đừng ngần ngại liên hệ chuyên gia theo số: \n024.3557.8387. \nHy vọng qua những thông tin này, câu hỏi"
  },
  {
    "id": "chunk_17",
    "chunk_index": 17,
    "source": "https://suckhoedoisong.vn/hoi-dap-tre-cham-noi-lieu-co-mac-tu-ky-169230404102526476.htm",
    "source_type": "docs",
    "url": "https://suckhoedoisong.vn/hoi-dap-tre-cham-noi-lieu-co-mac-tu-ky-169230404102526476.htm",
    "data_type": "web",
    "created_at": "2026-05-02T17:19:32.694461+00:00",
    "text": "024.3557.8387. \nHy vọng qua những thông tin này, câu hỏi \n\"Trẻ chậm nói liệu có mắc tự kỷ hay không?\"\n sẽ không còn là nỗi trăn trở của mỗi gia đình.\n*Thực phẩm này không phải là thuốc và không có tác dụng thay thế thuốc chữa bệnh.\nPV\n \n \n \nQuan tâm nhất\n \nMới nhất\nXem thêm bình luận\nÝ kiến của bạn\n \n \nHãy nhập họ và tên\n \n \nĐăng nhập để tham gia bình luận\n \n \nBình luận không đăng nhập\n \nGửi\nĐăng nhập\nThông báo\n \n \nBạn đã gửi thành công.\n Chia sẻ facebook \n \n \n \n \n Tags:\ntrẻ chậm nói"
  },
  {
    "id": "chunk_18",
    "chunk_index": 18,
    "source": "https://suckhoedoisong.vn/hoi-dap-tre-cham-noi-lieu-co-mac-tu-ky-169230404102526476.htm",
    "source_type": "docs",
    "url": "https://suckhoedoisong.vn/hoi-dap-tre-cham-noi-lieu-co-mac-tu-ky-169230404102526476.htm",
    "data_type": "web",
    "created_at": "2026-05-02T17:19:32.694461+00:00",
    "text": "Gửi\nĐăng nhập\nThông báo\n \n \nBạn đã gửi thành công.\n Chia sẻ facebook \n \n \n \n \n Tags:\ntrẻ chậm nói\nphát triển ngôn ngữ\n \n \n \n \nThời sự\n Xã hội \n \n Pháp luật \n \n Quốc tế \nY tế \n Tin nóng y tế \n \n Thành tựu y khoa \n \n Blog thầy thuốc \n \n Sự hi sinh thầm lặng \n \n Camera bệnh viện \nTra cứu bệnh\nSức khỏe TV\n Tọa đàm \n \n Giao lưu \n \n Livestream \nDược\n An toàn dùng thuốc \n \n Thông tin dược học \n \n Thuốc mới \n \n Vaccine \nY học cổ truyền\n Thầy giỏi – thuốc hay \n \n Bệnh viện - phòng khám"
  },
  {
    "id": "chunk_19",
    "chunk_index": 19,
    "source": "https://suckhoedoisong.vn/hoi-dap-tre-cham-noi-lieu-co-mac-tu-ky-169230404102526476.htm",
    "source_type": "docs",
    "url": "https://suckhoedoisong.vn/hoi-dap-tre-cham-noi-lieu-co-mac-tu-ky-169230404102526476.htm",
    "data_type": "web",
    "created_at": "2026-05-02T17:19:32.694461+00:00",
    "text": "Thuốc mới \n \n Vaccine \nY học cổ truyền\n Thầy giỏi – thuốc hay \n \n Bệnh viện - phòng khám \n \n Cây thuốc quanh ta \n \n Chữa bệnh không dùng thuốc \nMultimedia\n Emagazine \n \n Video \n \n Infographic \nY học 360\n Bệnh người cao tuổi \n \n Bệnh thường gặp \n \n Bệnh phụ nữ \n \n Bệnh nam giới \n \n Bệnh trẻ em \n \n Sức khỏe tâm hồn \n \n Ung thư \nKhỏe - Đẹp\n Mỹ phẩm \n \n Thẩm mỹ \n \n Bài tập khỏe đẹp \nDinh dưỡng\n Dinh dưỡng mẹ và bé \n \n Dinh dưỡng người cao tuổi \n \n Chế độ ăn người bệnh \n \n Cảnh giác thực phẩm"
  },
  {
    "id": "chunk_20",
    "chunk_index": 20,
    "source": "https://suckhoedoisong.vn/hoi-dap-tre-cham-noi-lieu-co-mac-tu-ky-169230404102526476.htm",
    "source_type": "docs",
    "url": "https://suckhoedoisong.vn/hoi-dap-tre-cham-noi-lieu-co-mac-tu-ky-169230404102526476.htm",
    "data_type": "web",
    "created_at": "2026-05-02T17:19:32.694461+00:00",
    "text": "Dinh dưỡng người cao tuổi \n \n Chế độ ăn người bệnh \n \n Cảnh giác thực phẩm \n \n Thực phẩm chức năng \nGiới tính\n Hỏi đáp phòng the \n \n Sức khỏe sinh sản \n \n Bệnh lây truyền \nPhòng mạch online\nThị trường\n Nhãn hàng sai phạm \n \n Doanh nghiệp \nNhịp cầu Nhân ái\nVăn hóa – Giải trí\nChuyên trang gia đình\nĐời sống\n \n \nTổng Biên tập: \nTRẦN TUẤN LINH\nPhó Tổng Biên tập: \nTÔ QUANG TRUNG\n (Thường trực), \nTRẦN YẾN CHÂU\n, \nNGUYỄN NGỌC ĐỨC\n, \nNGUYỄN CHÍ LONG"
  },
  {
    "id": "chunk_21",
    "chunk_index": 21,
    "source": "https://suckhoedoisong.vn/hoi-dap-tre-cham-noi-lieu-co-mac-tu-ky-169230404102526476.htm",
    "source_type": "docs",
    "url": "https://suckhoedoisong.vn/hoi-dap-tre-cham-noi-lieu-co-mac-tu-ky-169230404102526476.htm",
    "data_type": "web",
    "created_at": "2026-05-02T17:19:32.694461+00:00",
    "text": "TÔ QUANG TRUNG\n (Thường trực), \nTRẦN YẾN CHÂU\n, \nNGUYỄN NGỌC ĐỨC\n, \nNGUYỄN CHÍ LONG\nGiấy phép hoạt động báo chí số 390/GP-BTTTT do Bộ Thông tin và Truyền thông cấp ngày 25/06/2021\n© Bản quyền thuộc Báo điện tử Sức khỏe và Đời sống - Cơ quan ngôn luận của Bộ Y tế.\n \n \n \n \n \n \n \n \nLiên hệ\nTHÔNG TIN TÒA SOẠN\n \nTrụ sở chính:\n 138A Giảng Võ, phường Giảng Võ, TP Hà Nội\n \nĐịa chỉ nhận công văn, tài liệu và thư bạn đọc:\n Tầng 11 Trụ sở các cơ quan Bộ Y tế, ngõ 19 Duy Tân, phường Cầu Giấy, TP Hà Nội"
  },
  {
    "id": "chunk_22",
    "chunk_index": 22,
    "source": "https://suckhoedoisong.vn/hoi-dap-tre-cham-noi-lieu-co-mac-tu-ky-169230404102526476.htm",
    "source_type": "docs",
    "url": "https://suckhoedoisong.vn/hoi-dap-tre-cham-noi-lieu-co-mac-tu-ky-169230404102526476.htm",
    "data_type": "web",
    "created_at": "2026-05-02T17:19:32.694461+00:00",
    "text": "Tầng 11 Trụ sở các cơ quan Bộ Y tế, ngõ 19 Duy Tân, phường Cầu Giấy, TP Hà Nội\n \nĐiện thoại:\n 024.6688.8900 - \nFax:\n 024.3844.3144\n \nĐường dây nóng:\n 0904.852.222\n \nEmail:\n toasoan@suckhoedoisong.vn\nLIÊN HỆ QUẢNG CÁO: \nXEM BÁO GIÁ\nĐiện thoại:\n 0888.669.909 - \nEmail:\n ads@suckhoedoisong.vn\nVĂN PHÒNG ĐẠI DIỆN\n- Văn phòng đại diện phía Bắc: 55 Tuệ Tĩnh, phường Vinh Phú, tỉnh Nghệ An.\n - Văn phòng đại diện TPHCM: 213 Điện Biên Phủ, phường Xuân Hoà, TPHCM và 495 Điện Biên Phủ, phường Bàn Cờ, TPHCM."
  }
]